array_record/__init__.py
array_record/setup.py
array_record/beam/__init__.py
array_record/beam/arrayrecordio.py
array_record/beam/demo.py
array_record/beam/dofns.py
array_record/beam/example.py
array_record/beam/options.py
array_record/beam/pipelines.py
array_record/beam/testdata.py
array_record/python/__init__.py
array_record/python/array_record_data_source.py
array_record/python/array_record_data_source_test.py
array_record/python/array_record_module.so
array_record/python/array_record_module_test.py
array_record-0.8.1.dist-info/METADATA
array_record-0.8.1.dist-info/WHEEL
array_record-0.8.1.dist-info/top_level.txt
array_record-0.8.1.dist-info/RECORD
array_record-0.8.1.dist-info/licenses/LICENSE
